{"id":{"@type":"gremlin:int32","@value":1},"label":"person","outE":{"created":[{"id":{"@type":"gremlin:int32","@value":9},"inV":{"@type":"gremlin:int32","@value":3},"properties":{"weight":{"@type":"gremlin:double","@value":0.4}}}],"knows":[{"id":{"@type":"gremlin:int32","@value":7},"inV":{"@type":"gremlin:int32","@value":2},"properties":{"weight":{"@type":"gremlin:double","@value":0.5}}},{"id":{"@type":"gremlin:int32","@value":8},"inV":{"@type":"gremlin:int32","@value":4},"properties":{"weight":{"@type":"gremlin:double","@value":1.0}}}]},"properties":{"name":[{"id":{"@type":"gremlin:int64","@value":0},"value":"marko"}],"age":[{"id":{"@type":"gremlin:int64","@value":1},"value":{"@type":"gremlin:int32","@value":29}}]}}
{"id":{"@type":"gremlin:int32","@value":2},"label":"person","inE":{"knows":[{"id":{"@type":"gremlin:int32","@value":7},"outV":{"@type":"gremlin:int32","@value":1},"properties":{"weight":{"@type":"gremlin:double","@value":0.5}}}]},"properties":{"name":[{"id":{"@type":"gremlin:int64","@value":2},"value":"vadas"}],"age":[{"id":{"@type":"gremlin:int64","@value":3},"value":{"@type":"gremlin:int32","@value":27}}]}}
{"id":{"@type":"gremlin:int32","@value":3},"label":"software","inE":{"created":[{"id":{"@type":"gremlin:int32","@value":9},"outV":{"@type":"gremlin:int32","@value":1},"properties":{"weight":{"@type":"gremlin:double","@value":0.4}}},{"id":{"@type":"gremlin:int32","@value":11},"outV":{"@type":"gremlin:int32","@value":4},"properties":{"weight":{"@type":"gremlin:double","@value":0.4}}},{"id":{"@type":"gremlin:int32","@value":12},"outV":{"@type":"gremlin:int32","@value":6},"properties":{"weight":{"@type":"gremlin:double","@value":0.2}}}]},"properties":{"name":[{"id":{"@type":"gremlin:int64","@value":4},"value":"lop"}],"lang":[{"id":{"@type":"gremlin:int64","@value":5},"value":"java"}]}}
{"id":{"@type":"gremlin:int32","@value":4},"label":"person","inE":{"knows":[{"id":{"@type":"gremlin:int32","@value":8},"outV":{"@type":"gremlin:int32","@value":1},"properties":{"weight":{"@type":"gremlin:double","@value":1.0}}}]},"outE":{"created":[{"id":{"@type":"gremlin:int32","@value":10},"inV":{"@type":"gremlin:int32","@value":5},"properties":{"weight":{"@type":"gremlin:double","@value":1.0}}},{"id":{"@type":"gremlin:int32","@value":11},"inV":{"@type":"gremlin:int32","@value":3},"properties":{"weight":{"@type":"gremlin:double","@value":0.4}}}]},"properties":{"name":[{"id":{"@type":"gremlin:int64","@value":6},"value":"josh"}],"age":[{"id":{"@type":"gremlin:int64","@value":7},"value":{"@type":"gremlin:int32","@value":32}}]}}
{"id":{"@type":"gremlin:int32","@value":5},"label":"software","inE":{"created":[{"id":{"@type":"gremlin:int32","@value":10},"outV":{"@type":"gremlin:int32","@value":4},"properties":{"weight":{"@type":"gremlin:double","@value":1.0}}}]},"properties":{"name":[{"id":{"@type":"gremlin:int64","@value":8},"value":"ripple"}],"lang":[{"id":{"@type":"gremlin:int64","@value":9},"value":"java"}]}}
{"id":{"@type":"gremlin:int32","@value":6},"label":"person","outE":{"created":[{"id":{"@type":"gremlin:int32","@value":12},"inV":{"@type":"gremlin:int32","@value":3},"properties":{"weight":{"@type":"gremlin:double","@value":0.2}}}]},"properties":{"name":[{"id":{"@type":"gremlin:int64","@value":10},"value":"peter"}],"age":[{"id":{"@type":"gremlin:int64","@value":11},"value":{"@type":"gremlin:int32","@value":35}}]}}
